downcast.py
downcast-0.0.8.dist-info/LICENSE
downcast-0.0.8.dist-info/METADATA
downcast-0.0.8.dist-info/WHEEL
downcast-0.0.8.dist-info/top_level.txt
downcast-0.0.8.dist-info/RECORD
