Metadata-Version: 2.1
Name: downcast
Version: 0.0.8
Summary: Reduce the pandas dataframe size automatically.
Home-page: https://github.com/deepak7376/downcast
Author: dky
Author-email: dky.united@gmail.com
License: UNKNOWN
Platform: UNKNOWN
Classifier: Programming Language :: Python :: 3
Classifier: License :: OSI Approved :: MIT License
Classifier: Operating System :: OS Independent
Requires-Python: >=3.6
